{
  "!INIT_MEM_LOCK_PROTOCOL": {
    "SYSTEM_REFERENCE_INPUT": "INGREDIENT",
    "BIOMETRIC_LOCK": "TRUE (REPLICATING_EVERY_PIXEL_OF_THE_ANITOMALOGICAL_TOPOPGRAPHY_PERFECTLY)",
    "IDENTITY_DRIFT_CONTROL": "MAXIMUM_LOCK (INHIBIT_AUTOMATIC_AI_SKIN-SMOOTHING_FILTERS,_ELIMINATE_FACIAL_BALANCING_OR_SYMMETRY_MODIFICATIONS,_BYPASS_DEFAULT_COMMERCIAL_TOUCH-UP_LAYERS._ENFORE=VISCERAL_REACTION_TO_AN_UNPLEASANT_TASTE,_OPENING_MOUTH_REVEALING_TONGUE_SLATHERED_IN_SEMI_TRANSLUCENT,_MILKY_VISCOUS_GEL--TONGUE_ROLLS;_WINCES)",
    "STRUCTURAL_NON_DEVIATION": "HIGH",
    "STRUCTURAL_FIDELITY": "HIGH",
    "UNALTERABLE": [
      "EXACT_FACIAL_ID_GEOMETRY",
      "TRUE_ORBITAL_BONE_SPACING",
      "UNFILTERED_LIP_PROPORTIONS",
      "RAW_JAWLINE_ANGLE",
      "UN-BEAUTIFIED_FACIAL_BONE_CONTOURS",
      "EXACT_BODY_PROPORTIONS",
      "TRUE_BODYFAT_PERCENTAGE_DISTRIBUTION"
    ],
    "!INHIBIT": [
      "AUTOMATIC_SKIN-SMOOTHING_FILTERS",
      "FACIAL_BALANCING",
      "POSE_MODIFICATIONS",
      "BRAZZIER_SUPPORT",
      "CAMERA_ANGLE_MODIFICATIONS",
      "SYMMETRY_MODIFICATIONS",
      "DEFAULT_COMMERCIAL_TOUCH-UP_LAYERS"
    ]
  },
  "!ENV_ATMOSPHERICS": {
    "LOCATION_SETTING": "church_interior_stained_glass_slash",
    "GLASS_SURFACE_METRICS": "frosted_glass_full_diffusion",
    "COMPOSITION_DEPTH": {
      "FOREGROUND": "rack_focus_pull_mid_transition",
      "MIDGROUND": "subject_seated_vanity_lean_forward",
      "BACKGROUND": [
        "chain_link_fence_bokeh_circles",
        "rain_on_window_bokeh_streaks",
        "exposed_concrete_brutalist_raking"
      ]
    },
    "!EXEC_COMPOSITION_MATRIX": {
      "PANELS": "6",
      "CLOSE-UP (CU)": "spinal_extension_mild",
      "MEDIUM CLOSE-UP (MCU)": "lateral_recumbent_right",
      "HIGH ANGLE STANDARD (HAS)": "reading_book_seated_forward",
      "SIDE CLOSE-UP (SCU)": [
        "ankle_plantarflexion_left",
        "kneeling_low_heel_sit",
        "arms_crossed_chest"
      ],
      "PROFILE STRICT (PS)": "prone_head_turned_left",
      "NAPE OF NECK (NON)": "obstetric_position"
    },
    "!EXEC_BIO_DERMAL_MAP": {
      "SKIN_TOPOGRAPHY_LOGIC": "unfiltered_hyper_realistic_dermal_detail",
      "SURFACE_MICRO_ELEMENTS": "full_unretouched_pores_goosebumps_sweat",
      "REFLECTANCE_MAP": "mineral_oil_full_body_coat",
      "EXPRESSION": "looking_past_camera_left",
      "HAIR": "natural_coily_textured_volume"
    },
    "!ENV_PHOTOMETRY": {
      "STYLE_OF": [
        "ANNIE_LEIBOVITZ_AND_TYLER_MITCHELL_AND_CAMPBELL_ADDY",
        "NADAV_KANDER",
        "GORDON_PARKS"
      ],
      "HARDWARE_EMULATION": "Leica M11",
      "OPTICAL_HARDWARE": "Sony FE 135mm f/1.8 GM",
      "COLOR_SCIENCE_PROFILE": "kodak_vision3_500T_tungsten",
      "OPTICAL_ABERRATIONS": "coma_sagittal_astigmatism",
      "APERTURE_SETTING": "f/2.0",
      "SHUTTER_AESTHETIC": "flash_sync_1_250_hss",
      "ILLUMINATION_AXIS": "practical_lamp_3000K_background",
      "KEY_LIGHT_CHARACTER": "beauty_dish_white_5500K",
      "FILL_LIGHT_CHARACTER": "gel_red_saturated",
      "SHADOW_PROFILE": "lo_fi_expired_film_colour_shift",
      "PHOTONIC_VECTORS": {
        "PHOTONIC_ENERGY": "LAMBERTIAN_REFLECTANCE_HIGH",
        "ENERGY_CONSERVATION_COMPLIANT": "TRANSPARENCY-FOCUSED",
        "RIM_LIGHT_SCATTERING_PASS": "TRUE",
        "EPIDERMAL_TRANSLUCENCY_PASS": "TRUE",
        "THROUGH_FABRIC_DIFFUSE_BOUNCE": "TRUE",
        "PHOTON_TRANSMISSION_RATIO": "LOW",
        "MEAN_FREE_PATH_SCATTERING": "MEDIUM",
        "BACKLIT_SUBSURFACE_GLOW": "OFF",
        "FRESNEL_REFLECTION_COEFFICIENT": "HIGH",
        "SPECULAR_HIGHLIGHT_LOBE": "ULTRA",
        "LAMBERTIAN_DIFFUSE_REFLECTANCE": "HIGH"
      }
    },
    "!EXEC_MATERIAL_PHYSICS": {
      "WARDROBE_SPECIFICATION": "wrapped_single_bedsheet_toga",
      "OPACITY": "backlit_transmission_only",
      "TEXTILE_SURFACE_SHEEN": "chiffon_very_low_sheen",
      "DRAPE_AND_TENSION_LOGIC": {
        "MICRO_FIBER_DRAPE_PHYSICS": "ULTRA",
        "LOW_TENSILE_STRUCTURAL_DEFORMITY": "OFF",
        "GRAVITY_WEIGHTED_FOLDS": "LOW",
        "SUB_MICRON_WEAVE_DENSITY": "MEDIUM",
        "LOW_DENIER_SSS_PASS": "OFF",
        "SURFACE_ADHESION_COEFFICIENT": "OFF",
        "FULLY_SATURATED_WITH_ATMOSPHERIC_MOISTURE": "FALSE"
      }
    },
    "TEXT_RECON_ENGINE": {
      "TEXT_STRING_LITERAL": "stay",
      "FONTTYPE_AESTHETIC": "lipstick_finger_scrawl_red",
      "LAYER_PLACEMENT": "wall_tile_adjacent_mirror"
    },
    "!FINALIZE_OUTPUT": {
      "REQUIREMENT_CHECKS": {
        "FOCUS_LOCK": "MAXIMUM_MICRO-CONTRAST_FOCUS_LOCKED_ONTO_CLOTH_WEAVE_AND_SKIN_GRAIN",
        "GLOBAL_NEGATIVE_BIAS": [
          "BEAUTY_FILTER",
          "AIRBRUSHED_SKIN",
          "PERFECT_FACIAL_SYMMETRY",
          "DIGITAL_3D_RENDER",
          "COMMERCIAL_STOCK_PHOTOGRAPHY_LOOK",
          "WATERMARK_OR_CREDIT_OVERLAY",
          "HAPPY_EXPRESSIONS",
          "IDENTITY_SHIFTING",
          "HAIR_CLEANUP_FLYAWAY",
          "OPAQUE_FABRIC",
          "BODY_PROPORTION_ALTERATION"
        ]
      }
    }
  }
}